jupyter_vote/__init__.py
jupyter_vote/vote.py
jupyter_vote-0.3.0.dist-info/METADATA
jupyter_vote-0.3.0.dist-info/WHEEL
jupyter_vote-0.3.0.dist-info/RECORD
