Metadata-Version: 2.3
Name: jupyter-vote
Version: 0.3.0
Summary: EduVote integration for Jupyter notebooks
Author: dev@lkies.net
Requires-Python: >=3.10
Classifier: Programming Language :: Python :: 3
Classifier: Programming Language :: Python :: 3.10
Classifier: Programming Language :: Python :: 3.11
Classifier: Programming Language :: Python :: 3.12
Classifier: Programming Language :: Python :: 3.13
Requires-Dist: ipykernel (>=6.29.5,<7.0.0)
